ic50/__init__.py
ic50/ic50.py
ic50-0.0.99.3.dist-info/METADATA
ic50-0.0.99.3.dist-info/WHEEL
ic50-0.0.99.3.dist-info/top_level.txt
ic50-0.0.99.3.dist-info/RECORD
